swapper/__init__.py
swapper/__main__.py
swapper/swapper.py
ugrc_swapper-1.2.4.dist-info/licenses/LICENSE
ugrc_swapper-1.2.4.dist-info/METADATA
ugrc_swapper-1.2.4.dist-info/WHEEL
ugrc_swapper-1.2.4.dist-info/entry_points.txt
ugrc_swapper-1.2.4.dist-info/top_level.txt
ugrc_swapper-1.2.4.dist-info/RECORD
