Metadata-Version: 2.4
Name: ugrc-swapper
Version: 1.2.4
Summary: Move data from one SDE database to another with minimal downtime
Home-page: https://github.com/agrc/swapper
Author: UGRC
Author-email: ugrc-developers@utah.gov
License: MIT
Project-URL: Issue Tracker, https://github.com/agrc/swapper/issues
Keywords: gis
Classifier: Development Status :: 5 - Production/Stable
Classifier: Intended Audience :: Developers
Classifier: License :: OSI Approved :: MIT License
Classifier: Topic :: Utilities
License-File: LICENSE
Requires-Dist: docopt==0.*
Requires-Dist: python-dotenv==1.*
Requires-Dist: pyodbc==5.*
Requires-Dist: xxhash==3.*
Provides-Extra: tests
Requires-Dist: pytest-cov<8,>=5; extra == "tests"
Requires-Dist: pytest-instafail==0.5.*; extra == "tests"
Requires-Dist: pytest-mock==3.*; extra == "tests"
Requires-Dist: pytest-ruff==0.*; extra == "tests"
Requires-Dist: pytest-watch==4.*; extra == "tests"
Requires-Dist: pytest==8.*; extra == "tests"
Requires-Dist: black<26,>=24; extra == "tests"
Requires-Dist: ruff==0.*; extra == "tests"
Dynamic: author
Dynamic: author-email
Dynamic: classifier
Dynamic: description
Dynamic: description-content-type
Dynamic: home-page
Dynamic: keywords
Dynamic: license
Dynamic: license-file
Dynamic: project-url
Dynamic: provides-extra
Dynamic: requires-dist
Dynamic: summary
